{
    "Ar36": {
        "error": 2.103076281138727,
        "error_type": "",
        "fit": "previous",
        "references": [
            {
                "exclude": false,
                "record_id": "bc-03-N-10"
            }
        ],
        "value": 514.0611704892814
    },
    "Ar37": {
        "error": 2.483956536577434e-07,
        "error_type": "",
        "fit": "previous",
        "references": [
            {
                "exclude": false,
                "record_id": "bc-03-N-10"
            }
        ],
        "value": 4.852871970742878e-06
    },
    "Ar38": {
        "error": 2.511294528069371e-07,
        "error_type": "",
        "fit": "previous",
        "references": [
            {
                "exclude": false,
                "record_id": "bc-03-N-10"
            }
        ],
        "value": 2.603865324431874e-06
    },
    "Ar39": {
        "error": 1.41820587128907e-07,
        "error_type": "",
        "fit": "previous",
        "references": [
            {
                "exclude": false,
                "record_id": "bc-03-N-10"
            }
        ],
        "value": 9.40963147547169e-07
    },
    "Ar40": {
        "error": 1.3632416552576765e-06,
        "error_type": "",
        "fit": "previous",
        "references": [
            {
                "exclude": false,
                "record_id": "bc-03-N-10"
            }
        ],
        "value": 0.002694611088792387
    }
}